odoo/addons/sale_company_currency/README.rst
odoo/addons/sale_company_currency/__init__.py
odoo/addons/sale_company_currency/__manifest__.py
odoo/addons/sale_company_currency/i18n/ca.po
odoo/addons/sale_company_currency/i18n/de.po
odoo/addons/sale_company_currency/i18n/el_GR.po
odoo/addons/sale_company_currency/i18n/es.po
odoo/addons/sale_company_currency/i18n/es_ES.po
odoo/addons/sale_company_currency/i18n/es_VE.po
odoo/addons/sale_company_currency/i18n/fi.po
odoo/addons/sale_company_currency/i18n/fr.po
odoo/addons/sale_company_currency/i18n/hr.po
odoo/addons/sale_company_currency/i18n/hr_HR.po
odoo/addons/sale_company_currency/i18n/hu.po
odoo/addons/sale_company_currency/i18n/it.po
odoo/addons/sale_company_currency/i18n/nl.po
odoo/addons/sale_company_currency/i18n/nl_NL.po
odoo/addons/sale_company_currency/i18n/pt.po
odoo/addons/sale_company_currency/i18n/pt_BR.po
odoo/addons/sale_company_currency/i18n/ro.po
odoo/addons/sale_company_currency/i18n/sale_company_currency.pot
odoo/addons/sale_company_currency/i18n/sk.po
odoo/addons/sale_company_currency/i18n/sl.po
odoo/addons/sale_company_currency/i18n/tr.po
odoo/addons/sale_company_currency/i18n/tr_TR.po
odoo/addons/sale_company_currency/i18n/vi_VN.po
odoo/addons/sale_company_currency/i18n/zh_CN.po
odoo/addons/sale_company_currency/models/__init__.py
odoo/addons/sale_company_currency/models/sale_order.py
odoo/addons/sale_company_currency/readme/CONTRIBUTORS.rst
odoo/addons/sale_company_currency/readme/DESCRIPTION.rst
odoo/addons/sale_company_currency/static/description/icon.png
odoo/addons/sale_company_currency/static/description/index.html
odoo/addons/sale_company_currency/views/sale_order_view.xml
odoo14_addon_sale_company_currency-14.0.1.0.1.dist-info/METADATA
odoo14_addon_sale_company_currency-14.0.1.0.1.dist-info/WHEEL
odoo14_addon_sale_company_currency-14.0.1.0.1.dist-info/top_level.txt
odoo14_addon_sale_company_currency-14.0.1.0.1.dist-info/RECORD
